{
  "sections": {
    "main": {
      "type": "product-template_1",
      "blocks": {
        "e30652f7-a2be-485b-badf-5a5158a49fee": {
          "type": "badge",
          "settings": {
          }
        },
        "381d88fa-8256-4834-aa18-74f8c87ea99c": {
          "type": "title",
          "settings": {
          }
        },
        "37975a6d-6805-4e9c-bb8d-fa6109c9090f": {
          "type": "review_block",
          "settings": {
            "review_stars": 4,
            "no_of_reviews": 6
          }
        },
        "b01b3a19-14d9-4f02-bdba-8641889dd3ba": {
          "type": "price",
          "settings": {
          }
        },
        "5a68ab5f-f45d-4fc7-9b42-79a04ab0bc86": {
          "type": "text",
          "settings": {
            "text": "Shipping calculated at checkout."
          }
        },
        "c02813a5-2f3d-41e4-ab00-c8ae87f7ac2c": {
          "type": "variant_picker",
          "settings": {
          }
        },
        "d5d94b7d-9eed-47f1-ad92-84e03a0bd9ea": {
          "type": "gift_wrap_block",
          "settings": {
            "gift_wrap_text": "Gift wrap this product",
            "gift_wrap_checkbox": "unchecked"
          }
        },
        "b7768154-4467-42c2-a53a-29568a51a99c": {
          "type": "quantity_selector",
          "settings": {
          }
        },
        "8887ff95-f443-4ee2-a9cf-e927db766177": {
          "type": "buy_buttons",
          "settings": {
            "show_dynamic_checkout": true
          }
        },
        "361dc0e2-00ba-47d9-a7ee-0b897208f34b": {
          "type": "metafield_block",
          "settings": {
            "logo_limit": 4
          }
        },
        "9f389a2b-02c6-4c5b-9266-9acce6e9f88a": {
          "type": "share",
          "settings": {
            "share_text": "Share"
          }
        },
        "30377060-91a6-4af2-8f22-db0778872ab1": {
          "type": "social_logos",
          "settings": {
          }
        }
      },
      "block_order": [
        "e30652f7-a2be-485b-badf-5a5158a49fee",
        "381d88fa-8256-4834-aa18-74f8c87ea99c",
        "37975a6d-6805-4e9c-bb8d-fa6109c9090f",
        "b01b3a19-14d9-4f02-bdba-8641889dd3ba",
        "5a68ab5f-f45d-4fc7-9b42-79a04ab0bc86",
        "c02813a5-2f3d-41e4-ab00-c8ae87f7ac2c",
        "d5d94b7d-9eed-47f1-ad92-84e03a0bd9ea",
        "b7768154-4467-42c2-a53a-29568a51a99c",
        "8887ff95-f443-4ee2-a9cf-e927db766177",
        "361dc0e2-00ba-47d9-a7ee-0b897208f34b",
        "9f389a2b-02c6-4c5b-9266-9acce6e9f88a",
        "30377060-91a6-4af2-8f22-db0778872ab1"
      ],
      "settings": {
      }
    },
    "14d16ca1-4b35-4746-95e9-d8c295d46291": {
      "type": "customer-reviews-section",
      "blocks": {
        "cac7727c-5365-40da-afdb-1e93955d1925": {
          "type": "review_heading_block",
          "settings": {
            "total_review_stars": 5,
            "review_count": 5,
            "customer_action_text": "Write a review"
          }
        },
        "f63b816b-0b49-4184-8b18-d8e14f573925": {
          "type": "review_block",
          "settings": {
            "customer_review_stars": 5,
            "review_title": "Got it next day",
            "customer_name": "Layla Miller",
            "review_date": "22",
            "review_month": "Feb",
            "review_year": "2022",
            "review_paragraph": "<p>I just chose standard delivery and it still arrived next day, even when I placed the order at 10pm!!<\/p>",
            "report_text": "Report as inappropriate"
          }
        },
        "60ad41d5-4156-4b89-bef3-a67deccff6bf": {
          "type": "review_block",
          "settings": {
            "customer_review_stars": 5,
            "review_title": "Love these guys",
            "customer_name": "Ella Martinez",
            "review_date": "17",
            "review_month": "Feb",
            "review_year": "2022",
            "review_paragraph": "<p>I’m obsessed with this company. From their website to the little surprise you get in each delivery!<\/p>",
            "report_text": "Report as inappropriate"
          }
        },
        "ab7b9ef8-5121-4e8b-96df-31dd0fe22d0c": {
          "type": "review_block",
          "settings": {
            "customer_review_stars": 5,
            "review_title": "Support was fantastic",
            "customer_name": "Aria Hernande",
            "review_date": "07",
            "review_month": "Feb",
            "review_year": "2022",
            "review_paragraph": "<p>I spoke to Charlie on support when my delivery was delayed and he was great getting to the bottom of it. Turns out it was with a neighbour all along!<\/p>",
            "report_text": "Report as inappropriate"
          }
        },
        "c5cc5dc7-fe7c-4e15-ad94-001d06c2ac62": {
          "type": "review_block",
          "settings": {
            "customer_review_stars": 5,
            "review_title": "A must try",
            "customer_name": "Ellie Rodriguez ",
            "review_date": "04",
            "review_month": "Feb",
            "review_year": "2022",
            "review_paragraph": "<p>Do it, you won’t regret it!<\/p>",
            "report_text": "Report as inappropriate"
          }
        },
        "db2a8d11-9b9c-4e57-8ca5-a9e57c9e99f8": {
          "type": "review_block",
          "settings": {
            "customer_review_stars": 5,
            "review_title": "Service was incredible",
            "customer_name": "Avery Garcia",
            "review_date": "27",
            "review_month": "Jan",
            "review_year": "2022",
            "review_paragraph": "<p>I don’t like buying online so I spoke to support a lot before and after my purchase and they have always been really accommodating and understanding.<\/p>",
            "report_text": "Report as inappropriate"
          }
        }
      },
      "block_order": [
        "cac7727c-5365-40da-afdb-1e93955d1925",
        "f63b816b-0b49-4184-8b18-d8e14f573925",
        "60ad41d5-4156-4b89-bef3-a67deccff6bf",
        "ab7b9ef8-5121-4e8b-96df-31dd0fe22d0c",
        "c5cc5dc7-fe7c-4e15-ad94-001d06c2ac62",
        "db2a8d11-9b9c-4e57-8ca5-a9e57c9e99f8"
      ],
      "settings": {
        "background_color": "rgba(0,0,0,0)",
        "text_color": "#000000"
      }
    },
    "product-upsell": {
      "type": "marmeto-upsell",
      "disabled": true,
      "settings": {
        "enable_product_upselling": true,
        "title": "Upsell Products",
        "heading_text_color": "#000000",
        "heading_alignment": "text-center"
      }
    },
    "175ecb30-0f3d-48ba-8662-9cd024e62a53": {
      "type": "product-broad-description-section",
      "settings": {
        "visible_product_description": "<p>Relaxed boyfriend fit shirt dress in sand stripe soft and travel-friendly, wrinkle-resistant cotton blend shirting, features a classic open collar, full-button placket, and a shirttail hem.<\/p>",
        "opaque_product_description": "<p>Model is 177cm, wearing size S\/M.<br><br>Please note we do not offer exchange or refund on embroidered items as the garment is customised.<br><br>This is a demo store. This product can be bought on Pomme<\/p>",
        "readmore_text": "Read More",
        "readless_text": "Read Less"
      }
    },
    "product-recommendations": {
      "type": "marmeto-product-recommendations",
      "settings": {
        "enable_product_recommendations": true,
        "title": "You may also like",
        "heading_text_color": "#000000",
        "heading_alignment": "text-center"
      }
    },
    "956232e6-b4b0-4ad7-ae54-3fea81056d4f": {
      "type": "product-review-section",
      "blocks": {
        "26270bae-6e7a-4b2b-a942-4b9795adc2a5": {
          "type": "product_review_block",
          "settings": {
            "content_alignment": "text-center",
            "review_stars": 5,
            "stars_color": "#000000",
            "review_paragraph_text": "\"Our wedding prep photos are amazing and it's all thanks to Cannes and how amazing my bridesmaids looked.\"",
            "review_paragraph_text_color": "#000000",
            "author_name": "Olivia Smith",
            "author_text_color": "#000000"
          }
        },
        "d0c1fafb-1e4b-4765-bf70-e37985eb7a0d": {
          "type": "product_review_block",
          "settings": {
            "content_alignment": "text-center",
            "review_stars": 5,
            "stars_color": "#000000",
            "review_paragraph_text": "\"Our wedding prep photos are amazing and it's all thanks to Cannes and how amazing my bridesmaids looked.\"",
            "review_paragraph_text_color": "#000000",
            "author_name": "Olivia Smith",
            "author_text_color": "#000000"
          }
        },
        "f25ed4d1-ef54-4535-90ba-ddda00b4a5f8": {
          "type": "product_review_block",
          "settings": {
            "content_alignment": "text-center",
            "review_stars": 5,
            "stars_color": "#000000",
            "review_paragraph_text": "\"Our wedding prep photos are amazing and it's all thanks to Cannes and how amazing my bridesmaids looked.\"",
            "review_paragraph_text_color": "#000000",
            "author_name": "Olivia Smith",
            "author_text_color": "#000000"
          }
        }
      },
      "block_order": [
        "26270bae-6e7a-4b2b-a942-4b9795adc2a5",
        "d0c1fafb-1e4b-4765-bf70-e37985eb7a0d",
        "f25ed4d1-ef54-4535-90ba-ddda00b4a5f8"
      ],
      "settings": {
        "background_color": "#f8eeeb",
        "heading_text": "Customer Feedback",
        "heading_text_color": "#000000",
        "heading_text_alignment": "text-center"
      }
    },
    "6676cb02-2e00-4e85-ac7e-4f3f9f284700": {
      "type": "collage_1",
      "blocks": {
        "320d892e-e0a9-4dba-8f13-74ec3687f8a3": {
          "type": "collage-block",
          "settings": {
            "image": "shopify:\/\/shop_images\/bl_1.png",
            "heading_text": "",
            "heading_text_color": "#ffffff",
            "paragraph_text": "Shirts",
            "paragraph_text_color": "#ffffff",
            "text_alignment": "text-center",
            "button_text": "Shop Shirts",
            "button_background_color": "#37302c",
            "button_text_color": "#ffffff",
            "button_link": ""
          }
        },
        "f18bf654-e046-4c4d-a9d4-68af197954f7": {
          "type": "collage-block",
          "settings": {
            "image": "shopify:\/\/shop_images\/bl_2.png",
            "heading_text": "",
            "heading_text_color": "#000000",
            "paragraph_text": "Accessories",
            "paragraph_text_color": "#ffffff",
            "text_alignment": "text-center",
            "button_text": "Shop Accessories",
            "button_background_color": "#37302c",
            "button_text_color": "#ffffff",
            "button_link": ""
          }
        },
        "effed6a0-a553-4252-9fa5-c987ca115177": {
          "type": "collage-block",
          "settings": {
            "image": "shopify:\/\/shop_images\/bl_3.png",
            "image_mobile": "shopify:\/\/shop_images\/1_a12a3537-630c-45a0-9ade-f9be6da22e99.webp",
            "heading_text": "",
            "heading_text_color": "#000000",
            "paragraph_text": "Robes",
            "paragraph_text_color": "#ffffff",
            "text_alignment": "text-center",
            "button_text": "Shop Robes",
            "button_background_color": "#37302c",
            "button_text_color": "#ffffff",
            "button_link": ""
          }
        }
      },
      "block_order": [
        "320d892e-e0a9-4dba-8f13-74ec3687f8a3",
        "f18bf654-e046-4c4d-a9d4-68af197954f7",
        "effed6a0-a553-4252-9fa5-c987ca115177"
      ],
      "settings": {
        "paragraph_font_size": 20
      }
    },
    "f2534666-3546-4f9a-9ad8-d6764f311bec": {
      "type": "marmeto-recently-viewed-products",
      "settings": {
        "title": "Recently viewed"
      }
    }
  },
  "order": [
    "main",
    "14d16ca1-4b35-4746-95e9-d8c295d46291",
    "product-upsell",
    "175ecb30-0f3d-48ba-8662-9cd024e62a53",
    "product-recommendations",
    "956232e6-b4b0-4ad7-ae54-3fea81056d4f",
    "6676cb02-2e00-4e85-ac7e-4f3f9f284700",
    "f2534666-3546-4f9a-9ad8-d6764f311bec"
  ]
}